sigepy/__init__.py
sigepy/fourier.py
sigepy/ssi_cov.py
sigepy/utils.py
sigepy/wavelet.py
sigepy-0.1.5.dist-info/licenses/LICENSE
sigepy-0.1.5.dist-info/METADATA
sigepy-0.1.5.dist-info/WHEEL
sigepy-0.1.5.dist-info/top_level.txt
sigepy-0.1.5.dist-info/RECORD
