Metadata-Version: 2.4
Name: sigepy
Version: 0.1.5
Summary: estructuraPy Package for signal processing for structural vibrations analysis.
Author-email: Angel Navarro-Mora <ahnavarro@anmingenieria.com>
License: MIT License
Project-URL: Homepage, https://github.com/estructuraPy/sigepy
Classifier: Programming Language :: Python :: 3.12
Classifier: License :: OSI Approved :: MIT License
License-File: LICENSE
Dynamic: license-file
